pycurl_requests/__init__.py
pycurl_requests/__main__.py
pycurl_requests/api.py
pycurl_requests/auth.py
pycurl_requests/cookies.py
pycurl_requests/exceptions.py
pycurl_requests/models.py
pycurl_requests/sessions.py
pycurl_requests/structures.py
pycurl_requests/adapters/__init__.py
pycurl_requests/adapters/base.py
pycurl_requests/adapters/pycurl.py
pycurl_requests/tests/__init__.py
pycurl_requests/tests/test_auth.py
pycurl_requests/tests/test_exceptions.py
pycurl_requests/tests/test_requests.py
pycurl_requests/tests/test_session.py
pycurl_requests/tests/utils.py
pycurl_requests-0.5.0.dist-info/LICENSE
pycurl_requests-0.5.0.dist-info/METADATA
pycurl_requests-0.5.0.dist-info/WHEEL
pycurl_requests-0.5.0.dist-info/top_level.txt
pycurl_requests-0.5.0.dist-info/RECORD
