Metadata-Version: 2.1
Name: pycurl-requests
Version: 0.5.0
Summary: A Requests-compatible interface for pycURL
Home-page: https://github.com/dcoles/pycurl-requests
Classifier: Programming Language :: Python :: 3
Classifier: License :: OSI Approved :: MIT License
Classifier: Operating System :: OS Independent
Requires-Python: >=3.6
License-File: LICENSE
